qtip/__init__.py
qtip/score.py
qtip/ansible_library/__init__.py
qtip/ansible_library/modules/__init__.py
qtip/ansible_library/modules/apex_generate_inventory.py
qtip/ansible_library/modules/fuel.py
qtip/ansible_library/plugins/__init__.py
qtip/ansible_library/plugins/action/__init__.py
qtip/ansible_library/plugins/action/aggregate.py
qtip/ansible_library/plugins/action/calculate.py
qtip/ansible_library/plugins/action/collect.py
qtip/ansible_library/plugins/filter/__init__.py
qtip/ansible_library/plugins/filter/format.py
qtip/api/__init__.py
qtip/api/__main__.py
qtip/api/controllers/__init__.py
qtip/api/controllers/common.py
qtip/api/controllers/qpi.py
qtip/api/swagger/swagger.yaml
qtip/base/__init__.py
qtip/base/constant.py
qtip/base/error.py
qtip/cli/README.rst
qtip/cli/__init__.py
qtip/cli/entry.py
qtip/cli/utils.py
qtip/cli/commands/__init__.py
qtip/cli/commands/cmd_project.py
qtip/cli/commands/cmd_qpi.py
qtip/cli/commands/cmd_report.py
qtip/cli/templates/metric.j2
qtip/cli/templates/plan.j2
qtip/cli/templates/qpi.j2
qtip/collector/__init__.py
qtip/collector/logfile.py
qtip/collector/parser/__init__.py
qtip/collector/parser/grep.py
qtip/collector/transformer/__init__.py
qtip/collector/transformer/base.py
qtip/collector/transformer/timeline.py
qtip/loader/__init__.py
qtip/loader/base.py
qtip/loader/file.py
qtip/loader/qpi.py
qtip/loader/yaml_file.py
qtip/reporter/__init__.py
qtip/reporter/console.py
qtip/reporter/filters.py
qtip/reporter/testapi.py
qtip/reporter/templates/base.j2
qtip/reporter/templates/dpi.j2
qtip/reporter/templates/ramspeed.j2
qtip/reporter/templates/ssl.j2
qtip/reporter/templates/timeline.j2
qtip/reporter/templates/unixbench.j2
qtip/runner/__init__.py
qtip/runner/base.py
qtip/runner/project.py
qtip/scripts/qtip_creds.sh
qtip/scripts/quickstart.sh
qtip/util/__init__.py
qtip/util/dev.py
qtip/util/export_to.py
qtip/util/formula.py
qtip/util/logger.py
qtip/web/manage.py
qtip-5.0.0.dist-info/DESCRIPTION.rst
qtip-5.0.0.dist-info/METADATA
qtip-5.0.0.dist-info/RECORD
qtip-5.0.0.dist-info/WHEEL
qtip-5.0.0.dist-info/entry_points.txt
qtip-5.0.0.dist-info/metadata.json
qtip-5.0.0.dist-info/pbr.json
qtip-5.0.0.dist-info/top_level.txt
