Metadata-Version: 2.0
Name: qtip
Version: 5.0.0
Summary: Platform Performance Benchmarking
Home-page: https://wiki.opnfv.org/display/qtip
Author: OPNFV
Author-email: opnfv-tech-discuss@lists.opnfv.org
License: UNKNOWN
Platform: UNKNOWN
Requires-Dist: Django
Requires-Dist: Jinja2
Requires-Dist: PyYAML
Requires-Dist: ansible
Requires-Dist: asq
Requires-Dist: click
Requires-Dist: connexion (<=1.1.11)
Requires-Dist: humanfriendly
Requires-Dist: numpy
Requires-Dist: pbr
Requires-Dist: prettytable
Requires-Dist: requests
Requires-Dist: six
